zonpy/__init__.py
zonpy/lexer.py
zonpy/parser.py
zonpy-0.2.1.dist-info/LICENSE
zonpy-0.2.1.dist-info/METADATA
zonpy-0.2.1.dist-info/WHEEL
zonpy-0.2.1.dist-info/RECORD
