Metadata-Version: 2.1
Name: zonpy
Version: 0.2.1
Summary: Library for parsing and writing ZON (Zig Object Notation) files
License: MIT
Author: Mike Rivnak
Author-email: rivnakm1@gmail.com
Requires-Python: >=3.12,<4.0
Classifier: License :: OSI Approved :: MIT License
Classifier: Programming Language :: Python :: 3
Classifier: Programming Language :: Python :: 3.12
